clinkey_cli/__init__.py
clinkey_cli/cli.py
clinkey_cli/const.py
clinkey_cli/logos.py
clinkey_cli/main.py
clinkey_cli/settings.py
clinkey_cli/config/__init__.py
clinkey_cli/config/manager.py
clinkey_cli/generators/__init__.py
clinkey_cli/generators/base.py
clinkey_cli/generators/passphrase.py
clinkey_cli/generators/pattern.py
clinkey_cli/generators/registry.py
clinkey_cli/generators/syllable.py
clinkey_cli/security/__init__.py
clinkey_cli/security/analyzer.py
clinkey_cli/security/breach.py
clinkey_cli/security/compliance.py
clinkey_cli/security/context.py
clinkey_cli/security/dictionary.py
clinkey_cli/security/entropy.py
clinkey_cli/security/patterns.py
clinkey_cli/wordlists/__init__.py
clinkey_cli/wordlists/eff_large.json
clinkey_cli/wordlists/eff_large.py
clinkey_cli-2.0.1.dist-info/licenses/LICENSE
clinkey_cli-2.0.1.dist-info/METADATA
clinkey_cli-2.0.1.dist-info/WHEEL
clinkey_cli-2.0.1.dist-info/entry_points.txt
clinkey_cli-2.0.1.dist-info/top_level.txt
clinkey_cli-2.0.1.dist-info/RECORD
