Metadata-Version: 2.4
Name: clinkey-cli
Version: 2.0.1
Summary: A command-line tool for generating strong passwords and secret keys.
Author: Dimitri Gaggioli
License-Expression: MIT
Keywords: password,generator,cli,security
Classifier: Programming Language :: Python :: 3
Classifier: Operating System :: OS Independent
Classifier: Environment :: Console
Classifier: Topic :: Security
Classifier: Topic :: Utilities
Requires-Python: >=3.10
License-File: LICENSE
Requires-Dist: click>=8.3.1
Requires-Dist: rich>=14.2.0
Requires-Dist: httpx>=0.28.1
Requires-Dist: rich-click>=1.9.4
Provides-Extra: dev
Requires-Dist: pytest>=9.0.1; extra == "dev"
Requires-Dist: pytest-cov>=7.0.0; extra == "dev"
Requires-Dist: flake8>=7.3.0; extra == "dev"
Provides-Extra: build
Requires-Dist: build>=1.3.0; extra == "build"
Dynamic: license-file
